arctic3d/__init__.py
arctic3d/cli.py
arctic3d/cli_blast.py
arctic3d/cli_localise.py
arctic3d/cli_resclust.py
arctic3d/cli_restraints.py
arctic3d/functions.py
arctic3d/modules/__init__.py
arctic3d/modules/blast.py
arctic3d/modules/cluster_interfaces.py
arctic3d/modules/clustering.py
arctic3d/modules/example_clustering.py
arctic3d/modules/example_get_interface.py
arctic3d/modules/example_interface_matrix.py
arctic3d/modules/input.py
arctic3d/modules/interface.py
arctic3d/modules/interface_matrix.py
arctic3d/modules/log.py
arctic3d/modules/output.py
arctic3d/modules/pdb.py
arctic3d/modules/sequence.py
arctic3d/version.py
arctic3d-0.4.1.dist-info/METADATA
arctic3d-0.4.1.dist-info/WHEEL
arctic3d-0.4.1.dist-info/LICENSE
arctic3d-0.4.1.dist-info/entry_points.txt
arctic3d-0.4.1.dist-info/RECORD
