Metadata-Version: 2.1
Name: arctic3d
Version: 0.4.1
Summary: Automatic Retrieval and ClusTering of Interfaces in Complexes from 3D structural information
License: Apache-2.0
Author: BonvinLab
Author-email: bonvinlab.support@uu.nl
Requires-Python: >=3.9,<3.12
Classifier: Development Status :: 5 - Production/Stable
Classifier: Intended Audience :: Science/Research
Classifier: License :: OSI Approved :: Apache Software License
Classifier: Programming Language :: Python :: 3
Classifier: Programming Language :: Python :: 3.9
Classifier: Programming Language :: Python :: 3.10
Classifier: Programming Language :: Python :: 3.11
Classifier: Programming Language :: Python :: 3.9
Classifier: Topic :: Scientific/Engineering :: Bio-Informatics
Classifier: Topic :: Scientific/Engineering :: Chemistry
Requires-Dist: bio (==1.6.2)
Requires-Dist: biopython (==1.83)
Requires-Dist: defusedxml (==0.7.1)
Requires-Dist: jsonpickle (==3.0.3)
Requires-Dist: kaleido (==0.2.1)
Requires-Dist: lxml (==5.2.0)
Requires-Dist: matplotlib (==3.8.2)
Requires-Dist: mdanalysis (==2.7.0)
Requires-Dist: openpyxl (==3.1.2)
Requires-Dist: pandas (==2.2.1)
Requires-Dist: pdb-tools (==2.5.0)
Requires-Dist: pdbecif (==1.5)
Requires-Dist: plotly (==5.19.0)
Requires-Dist: requests (==2.31.0)
Requires-Dist: scipy (==1.12.0)
